{
  "friday": "Ningani",
  "title": "Zeidah sak na ka duh",
  "input": "Zei thil paoh ka hal tuah...",
  "search-short": "Kawl",
  "search-long": "Lawmhnak kawl .",
  "search-languages": "Caholh kawlnak",
  "new": "Hramthawknak thar",
  "home": "Inn",
  "automations": "Automation",
  "varients": "A phunphun",
  "library": "Caruuk",
  "projects": "Project",
  "spaces": "Hmunhma",
  "more": "Tam deuh",
  "info-title": "Info",
  "info-description": "Palhnak kan tuah khawhnak ding caah beta ah kan um rih.",
  "chat-history-notice": "Na chat tuanbia zoh khawhnak ding caah sign in tuah.",
  "sign-up": "min cazin tuah",
  "enter-signup-details": "Na konglam kha khumh law account tuah.",
  "create-account": "Account ser",
  "or-continue-with": "Asiloah 100 he pehzulh.",
  "already-have-account": "Account na ngei cang maw?",
  "sign-in": "Sign cu",
  "enter-login-details": "Na login kongkau kha khumh.",
  "forgot-password": "Password na philh maw?",
  "remember-me": "Ka philh tuah",
  "no-account": "Account na ngei lo maw?",
  "first-name": "Min hramthok",
  "last-name": "Min donghnak",
  "email": "email",
  "password": "Cafang thup",
  "confirm-password": "Password kha fehter",
  "confirm-password-placeholder": "Na password kha fehter",
  "profile-image-optional": "Profile Hmanthlak",
  "profile-preview-alt": "Profile preview",
  "sign-up-success": "Hlawhtling tein min cazin pe!",
  "upload-failed": "Upload a tling lo.",
  "profile-settings": "setting",
  "profile-pricing": "A man",
  "profile-documentation": "Cazin pek",
  "profile-community": "Zatlangbu",
  "profile-preferences": "Duhnak",
  "profile-theme": "A biatlangpi",
  "profile-language": "Holh",
  "sign-out": "Sign Out"
}