{
  "friday": "Aköl lɔ̈ŋ",
  "title": "Kë ya wïc ba yïk",
  "input": "Thiëc ɣɛn këriɛ̈ɛ̈c ëbɛ̈n...",
  "search-short": "Wïc",
  "search-long": "Tïŋ ë miɛt puɔ̈u",
  "search-languages": "Kɔc kɔɔr",
  "new": "Jɔ̈k ë yam",
  "home": "Baai",
  "automations": "Kä ye röt looi",
  "varients": "kɔc tuany",
  "library": "Athörluɔi",
  "projects": "kä ye röt looi",
  "spaces": "kë cït",
  "more": "Käjuëc",
  "info-title": "looi",
  "info-description": "Ɣok aŋot ke ɣok tɔ̈ në beta yic ku ɣok aa lëu buk käŋ wuɔ̈ɔ̈c.",
  "chat-history-notice": "Tääu ë yï nhom piny ba akököl de chat du tïŋ.",
  "sign-up": "Gät de wëu",
  "enter-signup-details": "Tääu ë wëlku yiic ba ɣön ë tɔ̈ɔ̈u looi.",
  "create-account": "Cäŋ këk",
  "or-continue-with": "Ku ŋoot ke lɔ tueŋ.",
  "already-have-account": "Tääu ë wëu ë thäät yiic?",
  "sign-in": "Tääu ë nhom në .",
  "enter-login-details": "Tääu ë wël ë lëkdu yic.",
  "forgot-password": "Kë cï yök në dhöl de gël de käŋ?",
  "remember-me": "Tath ɣa",
  "no-account": "Ku yïn acïn kë cï tääu thïn?",
  "first-name": "Rin tueŋ",
  "last-name": "Rin de raan",
  "email": "Eamia",
  "password": "Wɛ̈t puɔth",
  "confirm-password": "Cɔk ye raan ye wël rac lueel",
  "confirm-password-placeholder": "Cɔk wëlkuun ë lëkdu cɔɔl",
  "profile-image-optional": "Thura de kä ye nyuɔɔth",
  "profile-preview-alt": "Kë thiekic",
  "sign-up-success": "Gät yï rin ke yïn cï tiɛ̈m!",
  "upload-failed": "Uplolo acï thök.",
  "profile-settings": "Käk",
  "profile-pricing": "Wël",
  "profile-documentation": "Luɔɔi",
  "profile-community": "Akutnhom de kɔ̈c",
  "profile-preferences": "Ee yic",
  "profile-theme": "Bɛ̈r",
  "profile-language": "Thoŋ",
  "sign-out": "Athöör"
}